src/__init__.py
src/__main__.py
src/utils/__init__.py
src/utils/delete.py
src/utils/upload.py
src/utils/utils.py
cloudflare_gateway_adblocking-0.1.4.dist-info/LICENSE
cloudflare_gateway_adblocking-0.1.4.dist-info/METADATA
cloudflare_gateway_adblocking-0.1.4.dist-info/WHEEL
cloudflare_gateway_adblocking-0.1.4.dist-info/entry_points.txt
cloudflare_gateway_adblocking-0.1.4.dist-info/RECORD
