Metadata-Version: 2.1
Name: cloudflare-gateway-adblocking
Version: 0.1.4
Summary: Serverless adblocking via Cloudflare Zero Trust Gateway
Home-page: https://github.com/slashtechno/cloudflare-gateway-adblocking
License: MIT
Keywords: cloudflare,dns,adblocking,serverless
Author: slastechno
Author-email: 77907286+slashtechno@users.noreply.github.com
Requires-Python: >=3.10,<4.0
Classifier: License :: OSI Approved :: MIT License
Classifier: Programming Language :: Python :: 3
Classifier: Programming Language :: Python :: 3.10
Classifier: Programming Language :: Python :: 3.11
Classifier: Programming Language :: Python :: 3.12
Requires-Dist: httpx (>=0.24.1,<0.25.0)
Requires-Dist: loguru (>=0.7.0,<0.8.0)
Requires-Dist: python-dotenv (>=1.0.0,<2.0.0)
Requires-Dist: requests (>=2.31.0,<3.0.0)
Project-URL: Repository, https://github.com/slashtechno/cloudflare-gateway-adblocking
